pygments_style_apprentice/__init__.py
pygments_style_apprentice/style.py
pygments_style_apprentice-0.1.0.dist-info/DESCRIPTION.rst
pygments_style_apprentice-0.1.0.dist-info/METADATA
pygments_style_apprentice-0.1.0.dist-info/RECORD
pygments_style_apprentice-0.1.0.dist-info/WHEEL
pygments_style_apprentice-0.1.0.dist-info/entry_points.txt
pygments_style_apprentice-0.1.0.dist-info/metadata.json
pygments_style_apprentice-0.1.0.dist-info/pbr.json
pygments_style_apprentice-0.1.0.dist-info/top_level.txt
